tmlpy/__init__.py
tmlpy/parser.py
tmlpy/parser_test.py
tmlpy/tags.py
tmlpy/tml.py
tmlpy-0.1.0.dist-info/METADATA
tmlpy-0.1.0.dist-info/WHEEL
tmlpy-0.1.0.dist-info/top_level.txt
tmlpy-0.1.0.dist-info/RECORD
