Metadata-Version: 2.1
Name: tmlpy
Version: 0.1.0
Summary: Python implementation of Terminal Markup Language
Home-page: https://github.com/gaoliang/tmlpy
Author: gao liang
Author-email: me@gaoliang.im
License: MIT
Platform: UNKNOWN
Classifier: License :: OSI Approved :: MIT License
Classifier: Programming Language :: Python
Classifier: Programming Language :: Python :: 3
Classifier: Programming Language :: Python :: 3.6
Classifier: Programming Language :: Python :: Implementation :: CPython
Classifier: Programming Language :: Python :: Implementation :: PyPy
Requires-Python: >=3.6.0
